{
"data": [
{"ID" : "http://aims.fao.org/aos/agrovoc/xl_en_1299510026532",  "Name" : "producer prices@en" , "Count" : 48, "Links" : ["http://metadata.demo.52north.org/glues-lod/record/glues:ilr:metadata:dataset:producerprice-potatoes" , "http://metadata.demo.52north.org/glues-lod/record/glues:ilr:metadata:dataset:producerprice-soyacake" , "http://metadata.demo.52north.org/glues-lod/record/glues:ilr:metadata:dataset:producerprice-bioethanol" , "http://metadata.demo.52north.org/glues-lod/record/glues:ilr:metadata:dataset:producerprice-tobacco" , "http://metadata.demo.52north.org/glues-lod/record/glues:ilr:metadata:dataset:producerprice-oats" , "http://metadata.demo.52north.org/glues-lod/record/glues:ilr:metadata:dataset:producerprice-wholemilkpowder" , "http://metadata.demo.52north.org/glues-lod/record/glues:ilr:metadata:dataset:producerprice-sheepandgoatmeat" , "http://metadata.demo.52north.org/glues-lod/record/glues:ilr:metadata:dataset:producerprice-rapeseed" , "http://metadata.demo.52north.org/glues-lod/record/glues:ilr:metadata:dataset:producerprice-pulses" , "http://metadata.demo.52north.org/glues-lod/record/glues:ilr:metadata:dataset:producerprice-concentratedmilk" , "http://metadata.demo.52north.org/glues-lod/record/glues:ilr:metadata:dataset:producerprice-biodiesel" , "http://metadata.demo.52north.org/glues-lod/record/glues:ilr:metadata:dataset:producerprice-sunflowerseed" , "http://metadata.demo.52north.org/glues-lod/record/glues:ilr:metadata:dataset:producerprice-sunfloweroil" , "http://metadata.demo.52north.org/glues-lod/record/glues:ilr:metadata:dataset:producerprice-poultrymeat" , "http://metadata.demo.52north.org/glues-lod/record/glues:ilr:metadata:dataset:producerprice-skimmedmilkpowder" , "http://metadata.demo.52north.org/glues-lod/record/glues:ilr:metadata:dataset:producerprice-beefmeat" , "http://metadata.demo.52north.org/glues-lod/record/glues:ilr:metadata:dataset:producerprice-tableolives" , "http://metadata.demo.52north.org/glues-lod/record/glues:ilr:metadata:dataset:producerprice-tablewine" , "http://metadata.demo.52north.org/glues-lod/record/glues:ilr:metadata:dataset:producerprice-butter" , "http://metadata.demo.52north.org/glues-lod/record/glues:ilr:metadata:dataset:producerprice-rapeoil" , "http://metadata.demo.52north.org/glues-lod/record/glues:ilr:metadata:dataset:producerprice-otherfruits" , "http://metadata.demo.52north.org/glues-lod/record/glues:ilr:metadata:dataset:producerprice-porkmeat" , "http://metadata.demo.52north.org/glues-lod/record/glues:ilr:metadata:dataset:producerprice-ryeandmeslin" , "http://metadata.demo.52north.org/glues-lod/record/glues:ilr:metadata:dataset:producerprice-othercereals" , "http://metadata.demo.52north.org/glues-lod/record/glues:ilr:metadata:dataset:producerprice-rapeseedcake" , "http://metadata.demo.52north.org/glues-lod/record/glues:ilr:metadata:dataset:producerprice-cheese" , "http://metadata.demo.52north.org/glues-lod/record/glues:ilr:metadata:dataset:producerprice-tomatoes" , "http://metadata.demo.52north.org/glues-lod/record/glues:ilr:metadata:dataset:producerprice-wheat" , "http://metadata.demo.52north.org/glues-lod/record/glues:ilr:metadata:dataset:producerprice-caseinandcaseinates" , "http://metadata.demo.52north.org/glues-lod/record/glues:ilr:metadata:dataset:producerprice-freshmilkproducts" , "http://metadata.demo.52north.org/glues-lod/record/glues:ilr:metadata:dataset:producerprice-corn" , "http://metadata.demo.52north.org/glues-lod/record/glues:ilr:metadata:dataset:producerprice-sugar" , "http://metadata.demo.52north.org/glues-lod/record/glues:ilr:metadata:dataset:producerprice-soybean" , "http://metadata.demo.52north.org/glues-lod/record/glues:ilr:metadata:dataset:producerprice-citrusfruits" , "http://metadata.demo.52north.org/glues-lod/record/glues:ilr:metadata:dataset:producerprice-barley" , "http://metadata.demo.52north.org/glues-lod/record/glues:ilr:metadata:dataset:producerprice-rootsandtubers" , "http://metadata.demo.52north.org/glues-lod/record/glues:ilr:metadata:dataset:producerprice-eggs" , "http://metadata.demo.52north.org/glues-lod/record/glues:ilr:metadata:dataset:producerprice-rice" , "http://metadata.demo.52north.org/glues-lod/record/glues:ilr:metadata:dataset:producerprice-sunflowerseedcake" , "http://metadata.demo.52north.org/glues-lod/record/glues:ilr:metadata:dataset:producerprice-palmoil" , "http://metadata.demo.52north.org/glues-lod/record/glues:ilr:metadata:dataset:producerprice-oliveoil" , "http://metadata.demo.52north.org/glues-lod/record/glues:ilr:metadata:dataset:producerprice-soyoil" , "http://metadata.demo.52north.org/glues-lod/record/glues:ilr:metadata:dataset:producerprice-othervegetables" , "http://metadata.demo.52north.org/glues-lod/record/glues:ilr:metadata:dataset:producerprice-cream" , "http://metadata.demo.52north.org/glues-lod/record/glues:ilr:metadata:dataset:producerprice-tablegrapes" , "http://metadata.demo.52north.org/glues-lod/record/glues:ilr:metadata:dataset:producerprice-textiles" , "http://metadata.demo.52north.org/glues-lod/record/glues:ilr:metadata:dataset:producerprice-wheypowder" , "http://metadata.demo.52north.org/glues-lod/record/glues:ilr:metadata:dataset:producerprice-rawmilkatdairy" ]},
{"ID" : "http://aims.fao.org/aos/agrovoc/xl_en_1299509969806",  "Name" : "acreage@en" , "Count" : 30, "Links" : ["http://metadata.demo.52north.org/glues-lod/record/glues:ilr:metadata:dataset:acreage-ryeandmeslin" , "http://metadata.demo.52north.org/glues-lod/record/glues:ilr:metadata:dataset:acreage-othercereals" , "http://metadata.demo.52north.org/glues-lod/record/glues:ilr:metadata:dataset:acreage-tablewine" , "http://metadata.demo.52north.org/glues-lod/record/glues:ilr:metadata:dataset:acreage-beefmeat" , "http://metadata.demo.52north.org/glues-lod/record/glues:ilr:metadata:dataset:acreage-citrusfruits" , "http://metadata.demo.52north.org/glues-lod/record/glues:ilr:metadata:dataset:acreage-porkmeat" , "http://metadata.demo.52north.org/glues-lod/record/glues:ilr:metadata:dataset:acreage-poultrymeat" , "http://metadata.demo.52north.org/glues-lod/record/glues:ilr:metadata:dataset:acreage-othervegetables" , "http://metadata.demo.52north.org/glues-lod/record/glues:ilr:metadata:dataset:acreage-sunflowerseed" , "http://metadata.demo.52north.org/glues-lod/record/glues:ilr:metadata:dataset:acreage-palmoil" , "http://metadata.demo.52north.org/glues-lod/record/glues:ilr:metadata:dataset:acreage-rootsandtubers" , "http://metadata.demo.52north.org/glues-lod/record/glues:ilr:metadata:dataset:acreage-barley" , "http://metadata.demo.52north.org/glues-lod/record/glues:ilr:metadata:dataset:acreage-soybean" , "http://metadata.demo.52north.org/glues-lod/record/glues:ilr:metadata:dataset:acreage-tableolives" , "http://metadata.demo.52north.org/glues-lod/record/glues:ilr:metadata:dataset:acreage-rice" , "http://metadata.demo.52north.org/glues-lod/record/glues:ilr:metadata:dataset:acreage-potatoes" , "http://metadata.demo.52north.org/glues-lod/record/glues:ilr:metadata:dataset:acreage-rawmilkatdairy" , "http://metadata.demo.52north.org/glues-lod/record/glues:ilr:metadata:dataset:acreage-otherfruits" , "http://metadata.demo.52north.org/glues-lod/record/glues:ilr:metadata:dataset:acreage-corn" , "http://metadata.demo.52north.org/glues-lod/record/glues:ilr:metadata:dataset:acreage-textiles" , "http://metadata.demo.52north.org/glues-lod/record/glues:ilr:metadata:dataset:acreage-tablegrapes" , "http://metadata.demo.52north.org/glues-lod/record/glues:ilr:metadata:dataset:acreage-rapeseed" , "http://metadata.demo.52north.org/glues-lod/record/glues:ilr:metadata:dataset:acreage-eggs" , "http://metadata.demo.52north.org/glues-lod/record/glues:ilr:metadata:dataset:acreage-wheat" , "http://metadata.demo.52north.org/glues-lod/record/glues:ilr:metadata:dataset:acreage-sheepandgoatmeat" , "http://metadata.demo.52north.org/glues-lod/record/glues:ilr:metadata:dataset:acreage-sugar" , "http://metadata.demo.52north.org/glues-lod/record/glues:ilr:metadata:dataset:acreage-tobacco" , "http://metadata.demo.52north.org/glues-lod/record/glues:ilr:metadata:dataset:acreage-pulses" , "http://metadata.demo.52north.org/glues-lod/record/glues:ilr:metadata:dataset:acreage-tomatoes" , "http://metadata.demo.52north.org/glues-lod/record/glues:ilr:metadata:dataset:acreage-oats" ]},
{"ID" : "http://aims.fao.org/aos/agrovoc/xl_en_1299510016192",  "Name" : "vapour pressure@en" , "Count" : 2, "Links" : ["http://metadata.demo.52north.org/glues-lod/record/9bc2f28c-7e45-4843-ba32-6143f82cec3a" , "http://metadata.demo.52north.org/glues-lod/record/bfbb82be-5731-4bd7-ba85-0e3ab0f96ac1" ]},
{"ID" : "http://aims.fao.org/aos/agrovoc/xl_en_1299510031047",  "Name" : "market prices@en" , "Count" : 48, "Links" : ["http://metadata.demo.52north.org/glues-lod/record/glues:ilr:metadata:dataset:marketprice-othervegetables" , "http://metadata.demo.52north.org/glues-lod/record/glues:ilr:metadata:dataset:marketprice-barley" , "http://metadata.demo.52north.org/glues-lod/record/glues:ilr:metadata:dataset:marketprice-rootsandtubers" , "http://metadata.demo.52north.org/glues-lod/record/glues:ilr:metadata:dataset:marketprice-palmoil" , "http://metadata.demo.52north.org/glues-lod/record/glues:ilr:metadata:dataset:marketprice-rapeseed" , "http://metadata.demo.52north.org/glues-lod/record/glues:ilr:metadata:dataset:marketprice-rawmilkatdairy" , "http://metadata.demo.52north.org/glues-lod/record/glues:ilr:metadata:dataset:marketprice-sheepandgoatmeat" , "http://metadata.demo.52north.org/glues-lod/record/glues:ilr:metadata:dataset:marketprice-tobacco" , "http://metadata.demo.52north.org/glues-lod/record/glues:ilr:metadata:dataset:marketprice-corn" , "http://metadata.demo.52north.org/glues-lod/record/glues:ilr:metadata:dataset:marketprice-sunflowerseedcake" , "http://metadata.demo.52north.org/glues-lod/record/glues:ilr:metadata:dataset:marketprice-otherfruits" , "http://metadata.demo.52north.org/glues-lod/record/glues:ilr:metadata:dataset:marketprice-wheat" , "http://metadata.demo.52north.org/glues-lod/record/glues:ilr:metadata:dataset:marketprice-sugar" , "http://metadata.demo.52north.org/glues-lod/record/glues:ilr:metadata:dataset:marketprice-biodiesel" , "http://metadata.demo.52north.org/glues-lod/record/glues:ilr:metadata:dataset:marketprice-tomatoes" , "http://metadata.demo.52north.org/glues-lod/record/glues:ilr:metadata:dataset:marketprice-tablegrapes" , "http://metadata.demo.52north.org/glues-lod/record/glues:ilr:metadata:dataset:marketprice-tablewine" , "http://metadata.demo.52north.org/glues-lod/record/glues:ilr:metadata:dataset:marketprice-eggs" , "http://metadata.demo.52north.org/glues-lod/record/glues:ilr:metadata:dataset:marketprice-rice" , "http://metadata.demo.52north.org/glues-lod/record/glues:ilr:metadata:dataset:marketprice-rapeoil" , "http://metadata.demo.52north.org/glues-lod/record/glues:ilr:metadata:dataset:marketprice-wholemilkpowder" , "http://metadata.demo.52north.org/glues-lod/record/glues:ilr:metadata:dataset:marketprice-pulses" , "http://metadata.demo.52north.org/glues-lod/record/glues:ilr:metadata:dataset:marketprice-beefmeat" , "http://metadata.demo.52north.org/glues-lod/record/glues:ilr:metadata:dataset:marketprice-cream" , "http://metadata.demo.52north.org/glues-lod/record/glues:ilr:metadata:dataset:marketprice-rapeseedcake" , "http://metadata.demo.52north.org/glues-lod/record/glues:ilr:metadata:dataset:marketprice-porkmeat" , "http://metadata.demo.52north.org/glues-lod/record/glues:ilr:metadata:dataset:marketprice-caseinandcaseinates" , "http://metadata.demo.52north.org/glues-lod/record/glues:ilr:metadata:dataset:marketprice-sunfloweroil" , "http://metadata.demo.52north.org/glues-lod/record/glues:ilr:metadata:dataset:marketprice-oliveoil" , "http://metadata.demo.52north.org/glues-lod/record/glues:ilr:metadata:dataset:marketprice-cheese" , "http://metadata.demo.52north.org/glues-lod/record/glues:ilr:metadata:dataset:marketprice-textiles" , "http://metadata.demo.52north.org/glues-lod/record/glues:ilr:metadata:dataset:marketprice-ryeandmeslin" , "http://metadata.demo.52north.org/glues-lod/record/glues:ilr:metadata:dataset:marketprice-othercereals" , "http://metadata.demo.52north.org/glues-lod/record/glues:ilr:metadata:dataset:marketprice-bioethanol" , "http://metadata.demo.52north.org/glues-lod/record/glues:ilr:metadata:dataset:marketprice-wheypowder" , "http://metadata.demo.52north.org/glues-lod/record/glues:ilr:metadata:dataset:marketprice-skimmedmilkpowder" , "http://metadata.demo.52north.org/glues-lod/record/glues:ilr:metadata:dataset:marketprice-soybean" , "http://metadata.demo.52north.org/glues-lod/record/glues:ilr:metadata:dataset:marketprice-butter" , "http://metadata.demo.52north.org/glues-lod/record/glues:ilr:metadata:dataset:marketprice-oats" , "http://metadata.demo.52north.org/glues-lod/record/glues:ilr:metadata:dataset:marketprice-poultrymeat" , "http://metadata.demo.52north.org/glues-lod/record/glues:ilr:metadata:dataset:marketprice-citrusfruits" , "http://metadata.demo.52north.org/glues-lod/record/glues:ilr:metadata:dataset:marketprice-potatoes" , "http://metadata.demo.52north.org/glues-lod/record/glues:ilr:metadata:dataset:marketprice-sunflowerseed" , "http://metadata.demo.52north.org/glues-lod/record/glues:ilr:metadata:dataset:marketprice-tableolives" , "http://metadata.demo.52north.org/glues-lod/record/glues:ilr:metadata:dataset:marketprice-soyacake" , "http://metadata.demo.52north.org/glues-lod/record/glues:ilr:metadata:dataset:marketprice-soyoil" , "http://metadata.demo.52north.org/glues-lod/record/glues:ilr:metadata:dataset:marketprice-concentratedmilk" , "http://metadata.demo.52north.org/glues-lod/record/glues:ilr:metadata:dataset:marketprice-freshmilkproducts" ]},
{"ID" : "http://aims.fao.org/aos/agrovoc/xl_en_1299510161741",  "Name" : "indicators@en" , "Count" : 64, "Links" : ["http://metadata.demo.52north.org/glues-lod/record/glues:pik:metadata:dataset:magpielongtermlandusenoco2-mpi-echam5-sresb2population" , "http://metadata.demo.52north.org/glues-lod/record/glues:pik:metadata:dataset:magpielongtermlanduseco2-mpi-echam5-sresb2gdppercapita" , "http://metadata.demo.52north.org/glues-lod/record/glues:pik:metadata:dataset:magpielongtermlandusenoco2-noclimatechange-sresb2population" , "http://metadata.demo.52north.org/glues-lod/record/glues:pik:metadata:dataset:magpielongtermlandusenoco2-echo-g-sresb1population" , "http://metadata.demo.52north.org/glues-lod/record/glues:pik:metadata:dataset:magpielongtermlanduseco2-noclimatechange-sresb2gdppercapita" , "http://metadata.demo.52north.org/glues-lod/record/glues:pik:metadata:dataset:magpielongtermlandusenoco2-noclimatechange-sresb2gdppercapita" , "http://metadata.demo.52north.org/glues-lod/record/glues:pik:metadata:dataset:magpielongtermlanduseco2-ukmo-hadcm3-sresb1population" , "http://metadata.demo.52north.org/glues-lod/record/glues:pik:metadata:dataset:magpielongtermlanduseco2-ukmo-hadcm3-sresa1gdppercapita" , "http://metadata.demo.52north.org/glues-lod/record/glues:pik:metadata:dataset:magpielongtermlandusenoco2-mpi-echam5-sresa2gdppercapita" , "http://metadata.demo.52north.org/glues-lod/record/glues:pik:metadata:dataset:magpielongtermlandusenoco2-ukmo-hadcm3-sresa1population" , "http://metadata.demo.52north.org/glues-lod/record/glues:pik:metadata:dataset:magpielongtermlanduseco2-mpi-echam5-sresb1population" , "http://metadata.demo.52north.org/glues-lod/record/glues:pik:metadata:dataset:magpielongtermlandusenoco2-echo-g-sresa2population" , "http://metadata.demo.52north.org/glues-lod/record/glues:pik:metadata:dataset:magpielongtermlanduseco2-ukmo-hadcm3-sresa2population" , "http://metadata.demo.52north.org/glues-lod/record/glues:pik:metadata:dataset:magpielongtermlanduseco2-mpi-echam5-sresa1gdppercapita" , "http://metadata.demo.52north.org/glues-lod/record/glues:pik:metadata:dataset:magpielongtermlandusenoco2-ukmo-hadcm3-sresa2gdppercapita" , "http://metadata.demo.52north.org/glues-lod/record/glues:pik:metadata:dataset:magpielongtermlanduseco2-ukmo-hadcm3-sresb1gdppercapita" , "http://metadata.demo.52north.org/glues-lod/record/glues:pik:metadata:dataset:magpielongtermlanduseco2-noclimatechange-sresa1gdppercapita" , "http://metadata.demo.52north.org/glues-lod/record/glues:pik:metadata:dataset:magpielongtermlandusenoco2-noclimatechange-sresa1gdppercapita" , "http://metadata.demo.52north.org/glues-lod/record/glues:pik:metadata:dataset:magpielongtermlanduseco2-mpi-echam5-sresa2population" , "http://metadata.demo.52north.org/glues-lod/record/glues:pik:metadata:dataset:magpielongtermlandusenoco2-ukmo-hadcm3-sresb1population" , "http://metadata.demo.52north.org/glues-lod/record/glues:pik:metadata:dataset:magpielongtermlanduseco2-mpi-echam5-sresb1gdppercapita" , "http://metadata.demo.52north.org/glues-lod/record/glues:pik:metadata:dataset:magpielongtermlandusenoco2-ukmo-hadcm3-sresb2gdppercapita" , "http://metadata.demo.52north.org/glues-lod/record/glues:pik:metadata:dataset:magpielongtermlanduseco2-noclimatechange-sresa1population" , "http://metadata.demo.52north.org/glues-lod/record/glues:pik:metadata:dataset:magpielongtermlanduseco2-noclimatechange-sresb1gdppercapita" , "http://metadata.demo.52north.org/glues-lod/record/glues:pik:metadata:dataset:magpielongtermlandusenoco2-noclimatechange-sresb1gdppercapita" , "http://metadata.demo.52north.org/glues-lod/record/glues:pik:metadata:dataset:magpielongtermlanduseco2-ukmo-hadcm3-sresb2population" , "http://metadata.demo.52north.org/glues-lod/record/glues:pik:metadata:dataset:magpielongtermlandusenoco2-mpi-echam5-sresa1gdppercapita" , "http://metadata.demo.52north.org/glues-lod/record/glues:pik:metadata:dataset:magpielongtermlanduseco2-ukmo-hadcm3-sresa1population" , "http://metadata.demo.52north.org/glues-lod/record/glues:pik:metadata:dataset:magpielongtermlanduseco2-mpi-echam5-sresb2population" , "http://metadata.demo.52north.org/glues-lod/record/glues:pik:metadata:dataset:magpielongtermlanduseco2-noclimatechange-sresb1population" , "http://metadata.demo.52north.org/glues-lod/record/glues:pik:metadata:dataset:magpielongtermlandusenoco2-ukmo-hadcm3-sresa1gdppercapita" , "http://metadata.demo.52north.org/glues-lod/record/glues:pik:metadata:dataset:magpielongtermlandusenoco2-mpi-echam5-sresb1gdppercapita" , "http://metadata.demo.52north.org/glues-lod/record/glues:pik:metadata:dataset:magpielongtermlandusenoco2-ukmo-hadcm3-sresb2population" , "http://metadata.demo.52north.org/glues-lod/record/glues:pik:metadata:dataset:magpielongtermlanduseco2-noclimatechange-sresa2population" , "http://metadata.demo.52north.org/glues-lod/record/glues:pik:metadata:dataset:magpielongtermlandusenoco2-ukmo-hadcm3-sresb1gdppercapita" , "http://metadata.demo.52north.org/glues-lod/record/glues:pik:metadata:dataset:magpielongtermlanduseco2-echo-g-sresa1population" , "http://metadata.demo.52north.org/glues-lod/record/glues:pik:metadata:dataset:magpielongtermlanduseco2-echo-g-sresa2gdppercapita" , "http://metadata.demo.52north.org/glues-lod/record/glues:pik:metadata:dataset:magpielongtermlandusenoco2-mpi-echam5-sresa1population" , "http://metadata.demo.52north.org/glues-lod/record/glues:pik:metadata:dataset:magpielongtermlandusenoco2-echo-g-sresa2gdppercapita" , "http://metadata.demo.52north.org/glues-lod/record/glues:pik:metadata:dataset:magpielongtermlandusenoco2-noclimatechange-sresa1population" , "http://metadata.demo.52north.org/glues-lod/record/glues:ext:brookings:metadata:dataset:politicalstability" , "http://metadata.demo.52north.org/glues-lod/record/glues:pik:metadata:dataset:magpielongtermlandusenoco2-mpi-echam5-sresb2gdppercapita" , "http://metadata.demo.52north.org/glues-lod/record/glues:pik:metadata:dataset:magpielongtermlanduseco2-echo-g-sresb2gdppercapita" , "http://metadata.demo.52north.org/glues-lod/record/glues:pik:metadata:dataset:magpielongtermlanduseco2-noclimatechange-sresb2population" , "http://metadata.demo.52north.org/glues-lod/record/glues:pik:metadata:dataset:magpielongtermlanduseco2-echo-g-sresb1population" , "http://metadata.demo.52north.org/glues-lod/record/glues:pik:metadata:dataset:magpielongtermlandusenoco2-echo-g-sresb2gdppercapita" , "http://metadata.demo.52north.org/glues-lod/record/glues:pik:metadata:dataset:magpielongtermlandusenoco2-mpi-echam5-sresb1population" , "http://metadata.demo.52north.org/glues-lod/record/glues:pik:metadata:dataset:magpielongtermlandusenoco2-noclimatechange-sresb1population" , "http://metadata.demo.52north.org/glues-lod/record/glues:pik:metadata:dataset:magpielongtermlanduseco2-ukmo-hadcm3-sresa2gdppercapita" , "http://metadata.demo.52north.org/glues-lod/record/glues:pik:metadata:dataset:magpielongtermlanduseco2-echo-g-sresa2population" , "http://metadata.demo.52north.org/glues-lod/record/glues:pik:metadata:dataset:magpielongtermlanduseco2-echo-g-sresa1gdppercapita" , "http://metadata.demo.52north.org/glues-lod/record/glues:pik:metadata:dataset:magpielongtermlandusenoco2-mpi-echam5-sresa2population" , "http://metadata.demo.52north.org/glues-lod/record/glues:pik:metadata:dataset:magpielongtermlandusenoco2-echo-g-sresb2population" , "http://metadata.demo.52north.org/glues-lod/record/glues:pik:metadata:dataset:magpielongtermlandusenoco2-noclimatechange-sresa2population" , "http://metadata.demo.52north.org/glues-lod/record/glues:pik:metadata:dataset:magpielongtermlandusenoco2-echo-g-sresa1gdppercapita" , "http://metadata.demo.52north.org/glues-lod/record/glues:pik:metadata:dataset:magpielongtermlandusenoco2-echo-g-sresa1population" , "http://metadata.demo.52north.org/glues-lod/record/glues:pik:metadata:dataset:magpielongtermlanduseco2-mpi-echam5-sresa2gdppercapita" , "http://metadata.demo.52north.org/glues-lod/record/glues:pik:metadata:dataset:magpielongtermlanduseco2-ukmo-hadcm3-sresb2gdppercapita" , "http://metadata.demo.52north.org/glues-lod/record/glues:pik:metadata:dataset:magpielongtermlanduseco2-noclimatechange-sresa2gdppercapita" , "http://metadata.demo.52north.org/glues-lod/record/glues:pik:metadata:dataset:magpielongtermlandusenoco2-noclimatechange-sresa2gdppercapita" , "http://metadata.demo.52north.org/glues-lod/record/glues:pik:metadata:dataset:magpielongtermlanduseco2-echo-g-sresb1gdppercapita" , "http://metadata.demo.52north.org/glues-lod/record/glues:pik:metadata:dataset:magpielongtermlanduseco2-echo-g-sresb2population" , "http://metadata.demo.52north.org/glues-lod/record/glues:pik:metadata:dataset:magpielongtermlanduseco2-mpi-echam5-sresa1population" , "http://metadata.demo.52north.org/glues-lod/record/glues:pik:metadata:dataset:magpielongtermlandusenoco2-echo-g-sresb1gdppercapita" ]},
{"ID" : "http://aims.fao.org/aos/agrovoc/xl_en_1299488125770",  "Name" : "temperature@en" , "Count" : 161, "Links" : ["http://metadata.demo.52north.org/glues-lod/record/glues:pik:metadata:dataset:gfdl-cm2.12.5ktemperature" , "http://metadata.demo.52north.org/glues-lod/record/glues:pik:metadata:dataset:gfdl-cm2.14.0ktemperature" , "http://metadata.demo.52north.org/glues-lod/record/glues:pik:metadata:dataset:cnrm-cm33.5ktemperature" , "http://metadata.demo.52north.org/glues-lod/record/glues:pik:metadata:dataset:cnrm-cm35.0ktemperature" , "http://metadata.demo.52north.org/glues-lod/record/115527c7-e248-48f5-87a1-0c834ee233d1" , "http://metadata.demo.52north.org/glues-lod/record/glues:pik:metadata:dataset:csiro-mk3.02.5ktemperature" , "http://metadata.demo.52north.org/glues-lod/record/glues:pik:metadata:dataset:csiro-mk3.04.0ktemperature" , "http://metadata.demo.52north.org/glues-lod/record/glues:pik:metadata:dataset:mri-cgcm2.3.24.5ktemperature" , "http://metadata.demo.52north.org/glues-lod/record/glues:pik:metadata:dataset:fgoals-g1.02.5ktemperature" , "http://metadata.demo.52north.org/glues-lod/record/glues:pik:metadata:dataset:echo-g1.5ktemperature" , "http://metadata.demo.52north.org/glues-lod/record/glues:pik:metadata:dataset:echo-g3.0ktemperature" , "http://metadata.demo.52north.org/glues-lod/record/glues:pik:metadata:dataset:miroc3.2(hires)2.0ktemperature" , "http://metadata.demo.52north.org/glues-lod/record/glues:pik:metadata:dataset:giss-er2.0ktemperature" , "http://metadata.demo.52north.org/glues-lod/record/6ff5f607-f7ee-4596-82a0-0747dd503190" , "http://metadata.demo.52north.org/glues-lod/record/glues:pik:metadata:dataset:miroc3.2(medres)2.5ktemperature" , "http://metadata.demo.52north.org/glues-lod/record/glues:pik:metadata:dataset:miroc3.2(medres)4.0ktemperature" , "http://metadata.demo.52north.org/glues-lod/record/glues:pik:metadata:dataset:ccsm33.0ktemperature" , "http://metadata.demo.52north.org/glues-lod/record/glues:pik:metadata:dataset:ccsm31.5ktemperature" , "http://metadata.demo.52north.org/glues-lod/record/glues-ext:badc:metadata:dataset:cruts3.1dailymeantemperature" , "http://metadata.demo.52north.org/glues-lod/record/glues:pik:metadata:dataset:cgcm3.1(t47)4.0ktemperature" , "http://metadata.demo.52north.org/glues-lod/record/glues:pik:metadata:dataset:cgcm3.1(t47)2.5ktemperature" , "http://metadata.demo.52north.org/glues-lod/record/glues:pik:metadata:dataset:gfdl-cm2.14.5ktemperature" , "http://metadata.demo.52north.org/glues-lod/record/glues:pik:metadata:dataset:pcm2.0ktemperature" , "http://metadata.demo.52north.org/glues-lod/record/glues:pik:metadata:dataset:ukmo-hadcm32.0ktemperature" , "http://metadata.demo.52north.org/glues-lod/record/glues:pik:metadata:dataset:ipsl-cm43.0ktemperature" , "http://metadata.demo.52north.org/glues-lod/record/glues:pik:metadata:dataset:ipsl-cm41.5ktemperature" , "http://metadata.demo.52north.org/glues-lod/record/glues:pik:metadata:dataset:echo-g2.5ktemperature" , "http://metadata.demo.52north.org/glues-lod/record/glues:pik:metadata:dataset:echo-g4.0ktemperature" , "http://metadata.demo.52north.org/glues-lod/record/glues:pik:metadata:dataset:fgoals-g1.04.5ktemperature" , "http://metadata.demo.52north.org/glues-lod/record/glues:pik:metadata:dataset:ukmo-hadgem13.5ktemperature" , "http://metadata.demo.52north.org/glues-lod/record/glues:pik:metadata:dataset:ukmo-hadgem15.0ktemperature" , "http://metadata.demo.52north.org/glues-lod/record/glues:pik:metadata:dataset:miroc3.2(hires)1.5ktemperature" , "http://metadata.demo.52north.org/glues-lod/record/ebf16f03-4c29-471b-ac79-c85a1dac6c16" , "http://metadata.demo.52north.org/glues-lod/record/9bc2f28c-7e45-4843-ba32-6143f82cec3a" , "http://metadata.demo.52north.org/glues-lod/record/glues:pik:metadata:dataset:giss-er1.5ktemperature" , "http://metadata.demo.52north.org/glues-lod/record/glues:pik:metadata:dataset:giss-er3.0ktemperature" , "http://metadata.demo.52north.org/glues-lod/record/glues:pik:metadata:dataset:miroc3.2(medres)4.5ktemperature" , "http://metadata.demo.52north.org/glues-lod/record/glues:pik:metadata:dataset:ccsm33.5ktemperature" , "http://metadata.demo.52north.org/glues-lod/record/glues:pik:metadata:dataset:ccsm35.0ktemperature" , "http://metadata.demo.52north.org/glues-lod/record/a6e5996c-54f2-4e9e-bbd4-7b9352a167cf" , "http://metadata.demo.52north.org/glues-lod/record/glues:pik:metadata:dataset:cgcm3.1(t47)4.5ktemperature" , "http://metadata.demo.52north.org/glues-lod/record/glues:pik:metadata:dataset:echam5-mpi-om2.0ktemperature" , "http://metadata.demo.52north.org/glues-lod/record/glues:pik:metadata:dataset:mri-cgcm2.3.22.0ktemperature" , "http://metadata.demo.52north.org/glues-lod/record/glues:pik:metadata:dataset:pcm2.5ktemperature" , "http://metadata.demo.52north.org/glues-lod/record/glues:pik:metadata:dataset:pcm4.0ktemperature" , "http://metadata.demo.52north.org/glues-lod/record/glues:pik:metadata:dataset:ukmo-hadcm32.5ktemperature" , "http://metadata.demo.52north.org/glues-lod/record/glues:pik:metadata:dataset:ukmo-hadcm34.0ktemperature" , "http://metadata.demo.52north.org/glues-lod/record/glues:pik:metadata:dataset:ipsl-cm42.5ktemperature" , "http://metadata.demo.52north.org/glues-lod/record/glues:pik:metadata:dataset:ipsl-cm44.0ktemperature" , "http://metadata.demo.52north.org/glues-lod/record/glues:pik:metadata:dataset:giss-eh1.5ktemperature" , "http://metadata.demo.52north.org/glues-lod/record/glues:pik:metadata:dataset:giss-eh3.0ktemperature" , "http://metadata.demo.52north.org/glues-lod/record/glues:pik:metadata:dataset:echo-g4.5ktemperature" , "http://metadata.demo.52north.org/glues-lod/record/glues:pik:metadata:dataset:inm-cm3.01.5ktemperature" , "http://metadata.demo.52north.org/glues-lod/record/glues:pik:metadata:dataset:inm-cm3.03.0ktemperature" , "http://metadata.demo.52north.org/glues-lod/record/glues:pik:metadata:dataset:miroc3.2(hires)3.5ktemperature" , "http://metadata.demo.52north.org/glues-lod/record/glues:pik:metadata:dataset:miroc3.2(hires)5.0ktemperature" , "http://metadata.demo.52north.org/glues-lod/record/glues:pik:metadata:dataset:giss-er3.5ktemperature" , "http://metadata.demo.52north.org/glues-lod/record/glues:pik:metadata:dataset:giss-er5.0ktemperature" , "http://metadata.demo.52north.org/glues-lod/record/glues:pik:metadata:dataset:gfdl-cm2.02.5ktemperature" , "http://metadata.demo.52north.org/glues-lod/record/glues:pik:metadata:dataset:gfdl-cm2.04.0ktemperature" , "http://metadata.demo.52north.org/glues-lod/record/glues:pik:metadata:dataset:gfdl-cm2.12.0ktemperature" , "http://metadata.demo.52north.org/glues-lod/record/glues:pik:metadata:dataset:cnrm-cm32.0ktemperature" , "http://metadata.demo.52north.org/glues-lod/record/glues:pik:metadata:dataset:pcm5.0ktemperature" , "http://metadata.demo.52north.org/glues-lod/record/glues:pik:metadata:dataset:mri-cgcm2.3.22.5ktemperature" , "http://metadata.demo.52north.org/glues-lod/record/glues:pik:metadata:dataset:pcm3.5ktemperature" , "http://metadata.demo.52north.org/glues-lod/record/glues:pik:metadata:dataset:echam5-mpi-om2.5ktemperature" , "http://metadata.demo.52north.org/glues-lod/record/glues:pik:metadata:dataset:echam5-mpi-om4.0ktemperature" , "http://metadata.demo.52north.org/glues-lod/record/glues:pik:metadata:dataset:mri-cgcm2.3.24.0ktemperature" , "http://metadata.demo.52north.org/glues-lod/record/glues:pik:metadata:dataset:ipsl-cm44.5ktemperature" , "http://metadata.demo.52north.org/glues-lod/record/glues:pik:metadata:dataset:giss-eh3.5ktemperature" , "http://metadata.demo.52north.org/glues-lod/record/glues:pik:metadata:dataset:giss-eh5.0ktemperature" , "http://metadata.demo.52north.org/glues-lod/record/glues:pik:metadata:dataset:miroc3.2(medres)2.0ktemperature" , "http://metadata.demo.52north.org/glues-lod/record/glues:pik:metadata:dataset:gfdl-cm2.04.5ktemperature" , "http://metadata.demo.52north.org/glues-lod/record/glues:pik:metadata:dataset:gfdl-cm2.11.5ktemperature" , "http://metadata.demo.52north.org/glues-lod/record/glues:pik:metadata:dataset:gfdl-cm2.13.0ktemperature" , "http://metadata.demo.52north.org/glues-lod/record/glues:pik:metadata:dataset:cgcm3.1(t47)2.0ktemperature" , "http://metadata.demo.52north.org/glues-lod/record/glues:pik:metadata:dataset:cnrm-cm32.5ktemperature" , "http://metadata.demo.52north.org/glues-lod/record/glues:pik:metadata:dataset:cnrm-cm34.0ktemperature" , "http://metadata.demo.52north.org/glues-lod/record/glues:pik:metadata:dataset:csiro-mk3.01.5ktemperature" , "http://metadata.demo.52north.org/glues-lod/record/glues:pik:metadata:dataset:csiro-mk3.03.0ktemperature" , "http://metadata.demo.52north.org/glues-lod/record/glues:pik:metadata:dataset:mri-cgcm2.3.23.5ktemperature" , "http://metadata.demo.52north.org/glues-lod/record/glues:pik:metadata:dataset:mri-cgcm2.3.25.0ktemperature" , "http://metadata.demo.52north.org/glues-lod/record/glues:pik:metadata:dataset:echam5-mpi-om4.5ktemperature" , "http://metadata.demo.52north.org/glues-lod/record/glues:pik:metadata:dataset:echo-g2.0ktemperature" , "http://metadata.demo.52north.org/glues-lod/record/glues:pik:metadata:dataset:fgoals-g1.04.0ktemperature" , "http://metadata.demo.52north.org/glues-lod/record/glues:pik:metadata:dataset:ukmo-hadgem11.5ktemperature" , "http://metadata.demo.52north.org/glues-lod/record/glues:pik:metadata:dataset:ukmo-hadgem13.0ktemperature" , "http://metadata.demo.52north.org/glues-lod/record/glues:pik:metadata:dataset:giss-eh4.5ktemperature" , "http://metadata.demo.52north.org/glues-lod/record/glues:pik:metadata:dataset:miroc3.2(medres)1.5ktemperature" , "http://metadata.demo.52north.org/glues-lod/record/glues:pik:metadata:dataset:inm-cm3.04.5ktemperature" , "http://metadata.demo.52north.org/glues-lod/record/glues:pik:metadata:dataset:ccsm32.0ktemperature" , "http://metadata.demo.52north.org/glues-lod/record/glues:pik:metadata:dataset:cgcm3.1(t47)1.5ktemperature" , "http://metadata.demo.52north.org/glues-lod/record/glues-ext:badc:metadata:dataset:cruts3.0dailymeantemperature" , "http://metadata.demo.52north.org/glues-lod/record/glues:pik:metadata:dataset:gfdl-cm2.13.5ktemperature" , "http://metadata.demo.52north.org/glues-lod/record/glues:pik:metadata:dataset:cgcm3.1(t47)3.0ktemperature" , "http://metadata.demo.52north.org/glues-lod/record/glues:pik:metadata:dataset:gfdl-cm2.15.0ktemperature" , "http://metadata.demo.52north.org/glues-lod/record/glues:pik:metadata:dataset:cnrm-cm34.5ktemperature" , "http://metadata.demo.52north.org/glues-lod/record/glues:pik:metadata:dataset:csiro-mk3.03.5ktemperature" , "http://metadata.demo.52north.org/glues-lod/record/glues:pik:metadata:dataset:csiro-mk3.05.0ktemperature" , "http://metadata.demo.52north.org/glues-lod/record/glues:pik:metadata:dataset:fgoals-g1.03.5ktemperature" , "http://metadata.demo.52north.org/glues-lod/record/glues:pik:metadata:dataset:ipsl-cm42.0ktemperature" , "http://metadata.demo.52north.org/glues-lod/record/glues:pik:metadata:dataset:fgoals-g1.05.0ktemperature" , "http://metadata.demo.52north.org/glues-lod/record/glues:pik:metadata:dataset:ukmo-hadgem12.5ktemperature" , "http://metadata.demo.52north.org/glues-lod/record/glues:pik:metadata:dataset:ukmo-hadgem14.0ktemperature" , "http://metadata.demo.52north.org/glues-lod/record/glues:pik:metadata:dataset:miroc3.2(hires)3.0ktemperature" , "http://metadata.demo.52north.org/glues-lod/record/glues:pik:metadata:dataset:miroc3.2(medres)5.0ktemperature" , "http://metadata.demo.52north.org/glues-lod/record/glues:pik:metadata:dataset:miroc3.2(medres)3.5ktemperature" , "http://metadata.demo.52north.org/glues-lod/record/glues:pik:metadata:dataset:gfdl-cm2.02.0ktemperature" , "http://metadata.demo.52north.org/glues-lod/record/glues:pik:metadata:dataset:ccsm32.5ktemperature" , "http://metadata.demo.52north.org/glues-lod/record/glues:pik:metadata:dataset:ccsm34.0ktemperature" , "http://metadata.demo.52north.org/glues-lod/record/glues:pik:metadata:dataset:cgcm3.1(t47)3.5ktemperature" , "http://metadata.demo.52north.org/glues-lod/record/glues:pik:metadata:dataset:cgcm3.1(t47)5.0ktemperature" , "http://metadata.demo.52north.org/glues-lod/record/glues:pik:metadata:dataset:pcm1.5ktemperature" , "http://metadata.demo.52north.org/glues-lod/record/glues:pik:metadata:dataset:pcm3.0ktemperature" , "http://metadata.demo.52north.org/glues-lod/record/glues:pik:metadata:dataset:ukmo-hadcm31.5ktemperature" , "http://metadata.demo.52north.org/glues-lod/record/glues:pik:metadata:dataset:ukmo-hadcm33.0ktemperature" , "http://metadata.demo.52north.org/glues-lod/record/glues:pik:metadata:dataset:csiro-mk3.04.5ktemperature" , "http://metadata.demo.52north.org/glues-lod/record/glues:pik:metadata:dataset:giss-eh2.0ktemperature" , "http://metadata.demo.52north.org/glues-lod/record/glues:pik:metadata:dataset:echo-g3.5ktemperature" , "http://metadata.demo.52north.org/glues-lod/record/glues:pik:metadata:dataset:echo-g5.0ktemperature" , "http://metadata.demo.52north.org/glues-lod/record/glues:pik:metadata:dataset:inm-cm3.02.0ktemperature" , "http://metadata.demo.52north.org/glues-lod/record/glues:pik:metadata:dataset:ukmo-hadgem14.5ktemperature" , "http://metadata.demo.52north.org/glues-lod/record/glues:pik:metadata:dataset:miroc3.2(hires)2.5ktemperature" , "http://metadata.demo.52north.org/glues-lod/record/glues:pik:metadata:dataset:miroc3.2(hires)4.0ktemperature" , "http://metadata.demo.52north.org/glues-lod/record/glues:pik:metadata:dataset:giss-er2.5ktemperature" , "http://metadata.demo.52north.org/glues-lod/record/glues:pik:metadata:dataset:giss-er4.0ktemperature" , "http://metadata.demo.52north.org/glues-lod/record/glues:pik:metadata:dataset:gfdl-cm2.03.0ktemperature" , "http://metadata.demo.52north.org/glues-lod/record/glues:pik:metadata:dataset:gfdl-cm2.01.5ktemperature" , "http://metadata.demo.52north.org/glues-lod/record/glues:pik:metadata:dataset:ccsm34.5ktemperature" , "http://metadata.demo.52north.org/glues-lod/record/glues:pik:metadata:dataset:echam5-mpi-om1.5ktemperature" , "http://metadata.demo.52north.org/glues-lod/record/glues:pik:metadata:dataset:echam5-mpi-om3.0ktemperature" , "http://metadata.demo.52north.org/glues-lod/record/glues:pik:metadata:dataset:mri-cgcm2.3.21.5ktemperature" , "http://metadata.demo.52north.org/glues-lod/record/glues:pik:metadata:dataset:mri-cgcm2.3.23.0ktemperature" , "http://metadata.demo.52north.org/glues-lod/record/6658f47c-8343-414f-a51b-8d12079d556d" , "http://metadata.demo.52north.org/glues-lod/record/glues:pik:metadata:dataset:ukmo-hadcm35.0ktemperature" , "http://metadata.demo.52north.org/glues-lod/record/glues:pik:metadata:dataset:ukmo-hadcm33.5ktemperature" , "http://metadata.demo.52north.org/glues-lod/record/glues:pik:metadata:dataset:giss-eh2.5ktemperature" , "http://metadata.demo.52north.org/glues-lod/record/glues:pik:metadata:dataset:ipsl-cm43.5ktemperature" , "http://metadata.demo.52north.org/glues-lod/record/glues:pik:metadata:dataset:ipsl-cm45.0ktemperature" , "http://metadata.demo.52north.org/glues-lod/record/glues:pik:metadata:dataset:giss-eh4.0ktemperature" , "http://metadata.demo.52north.org/glues-lod/record/glues:pik:metadata:dataset:inm-cm3.02.5ktemperature" , "http://metadata.demo.52north.org/glues-lod/record/glues:pik:metadata:dataset:inm-cm3.04.0ktemperature" , "http://metadata.demo.52north.org/glues-lod/record/glues:pik:metadata:dataset:miroc3.2(hires)4.5ktemperature" , "http://metadata.demo.52north.org/glues-lod/record/glues:pik:metadata:dataset:giss-er4.5ktemperature" , "http://metadata.demo.52north.org/glues-lod/record/glues:pik:metadata:dataset:gfdl-cm2.05.0ktemperature" , "http://metadata.demo.52north.org/glues-lod/record/glues:pik:metadata:dataset:gfdl-cm2.03.5ktemperature" , "http://metadata.demo.52north.org/glues-lod/record/06caa398-bf8d-47dd-9bea-7c44944c5823" , "http://metadata.demo.52north.org/glues-lod/record/glues:pik:metadata:dataset:cnrm-cm31.5ktemperature" , "http://metadata.demo.52north.org/glues-lod/record/glues:pik:metadata:dataset:cnrm-cm33.0ktemperature" , "http://metadata.demo.52north.org/glues-lod/record/glues:pik:metadata:dataset:csiro-mk3.02.0ktemperature" , "http://metadata.demo.52north.org/glues-lod/record/glues:pik:metadata:dataset:pcm4.5ktemperature" , "http://metadata.demo.52north.org/glues-lod/record/glues:pik:metadata:dataset:echam5-mpi-om3.5ktemperature" , "http://metadata.demo.52north.org/glues-lod/record/glues:pik:metadata:dataset:echam5-mpi-om5.0ktemperature" , "http://metadata.demo.52north.org/glues-lod/record/glues:pik:metadata:dataset:fgoals-g1.01.5ktemperature" , "http://metadata.demo.52north.org/glues-lod/record/glues:pik:metadata:dataset:fgoals-g1.03.0ktemperature" , "http://metadata.demo.52north.org/glues-lod/record/glues:pik:metadata:dataset:ukmo-hadcm34.5ktemperature" , "http://metadata.demo.52north.org/glues-lod/record/glues:pik:metadata:dataset:ukmo-hadgem12.0ktemperature" , "http://metadata.demo.52north.org/glues-lod/record/glues:pik:metadata:dataset:inm-cm3.03.5ktemperature" , "http://metadata.demo.52north.org/glues-lod/record/glues:pik:metadata:dataset:inm-cm3.05.0ktemperature" , "http://metadata.demo.52north.org/glues-lod/record/glues:pik:metadata:dataset:miroc3.2(medres)3.0ktemperature" , "http://metadata.demo.52north.org/glues-lod/record/a2cbbada-80b6-4ec2-9425-401e2bf789fe" ]},
{"ID" : "http://aims.fao.org/aos/agrovoc/xl_en_1299488532945",  "Name" : "runoff@en" , "Count" : 14, "Links" : ["http://metadata.demo.52north.org/glues-lod/record/glues:pik:metadata:dataset:piklimitedwcrpcmip3multi-modelimpactdataset-echo-gsresa2constantco2lpjmlrunoff" , "http://metadata.demo.52north.org/glues-lod/record/glues:pik:metadata:dataset:piklimitedwcrpcmip3multi-modelimpactdataset-echo-gsresb1dynamicco2lpjmlrunoff" , "http://metadata.demo.52north.org/glues-lod/record/glues:pik:metadata:dataset:piklimitedwcrpcmip3multi-modelimpactdataset-ukmo-hadcm3sresb1dynamicco2lpjmlrunoff" , "http://metadata.demo.52north.org/glues-lod/record/glues:pik:metadata:dataset:piklimitedwcrpcmip3multi-modelimpactdataset-echo-gsresa1bdynamicco2lpjmlrunoff" , "http://metadata.demo.52north.org/glues-lod/record/glues:pik:metadata:dataset:piklimitedwcrpcmip3multi-modelimpactdataset-echam5-mpi-omsresb1constantco2lpjmlrunoff" , "http://metadata.demo.52north.org/glues-lod/record/glues:pik:metadata:dataset:piklimitedwcrpcmip3multi-modelimpactdataset-echo-gsresa1bconstantco2lpjmlrunoff" , "http://metadata.demo.52north.org/glues-lod/record/glues:pik:metadata:dataset:piklimitedwcrpcmip3multi-modelimpactdataset-ukmo-hadcm3sresb1constantco2lpjmlrunoff" , "http://metadata.demo.52north.org/glues-lod/record/glues:pik:metadata:dataset:piklimitedwcrpcmip3multi-modelimpactdataset-echam5-mpi-omsresa2constantco2lpjmlrunoff" , "http://metadata.demo.52north.org/glues-lod/record/glues:pik:metadata:dataset:piklimitedwcrpcmip3multi-modelimpactdataset-echo-gsresa2dynamicco2lpjmlrunoff" , "http://metadata.demo.52north.org/glues-lod/record/glues:pik:metadata:dataset:piklimitedwcrpcmip3multi-modelimpactdataset-echam5-mpi-omsresa1bconstantco2lpjmlrunoff" , "http://metadata.demo.52north.org/glues-lod/record/glues:pik:metadata:dataset:piklimitedwcrpcmip3multi-modelimpactdataset-echam5-mpi-omsresa2dynamicco2lpjmlrunoff" , "http://metadata.demo.52north.org/glues-lod/record/glues:pik:metadata:dataset:piklimitedwcrpcmip3multi-modelimpactdataset-echam5-mpi-omsresa1bdynamicco2lpjmlrunoff" , "http://metadata.demo.52north.org/glues-lod/record/glues:pik:metadata:dataset:piklimitedwcrpcmip3multi-modelimpactdataset-echam5-mpi-omsresb1dynamicco2lpjmlrunoff" , "http://metadata.demo.52north.org/glues-lod/record/glues:pik:metadata:dataset:piklimitedwcrpcmip3multi-modelimpactdataset-echo-gsresb1constantco2lpjmlrunoff" ]},
{"ID" : "http://aims.fao.org/aos/agrovoc/xl_en_1299510166788",  "Name" : "gross domestic product@en" , "Count" : 33, "Links" : ["http://metadata.demo.52north.org/glues-lod/record/glues:pik:metadata:dataset:magpielongtermlanduseco2-mpi-echam5-sresb2gdppercapita" , "http://metadata.demo.52north.org/glues-lod/record/glues:pik:metadata:dataset:magpielongtermlanduseco2-noclimatechange-sresb2gdppercapita" , "http://metadata.demo.52north.org/glues-lod/record/glues:pik:metadata:dataset:magpielongtermlandusenoco2-noclimatechange-sresb2gdppercapita" , "http://metadata.demo.52north.org/glues-lod/record/glues:pik:metadata:dataset:magpielongtermlanduseco2-ukmo-hadcm3-sresa1gdppercapita" , "http://metadata.demo.52north.org/glues-lod/record/glues:pik:metadata:dataset:magpielongtermlandusenoco2-mpi-echam5-sresa2gdppercapita" , "http://metadata.demo.52north.org/glues-lod/record/glues:pik:metadata:dataset:magpielongtermlanduseco2-mpi-echam5-sresa1gdppercapita" , "http://metadata.demo.52north.org/glues-lod/record/glues:pik:metadata:dataset:magpielongtermlandusenoco2-ukmo-hadcm3-sresa2gdppercapita" , "http://metadata.demo.52north.org/glues-lod/record/glues:pik:metadata:dataset:magpielongtermlanduseco2-ukmo-hadcm3-sresb1gdppercapita" , "http://metadata.demo.52north.org/glues-lod/record/glues:pik:metadata:dataset:magpielongtermlanduseco2-noclimatechange-sresa1gdppercapita" , "http://metadata.demo.52north.org/glues-lod/record/glues:pik:metadata:dataset:magpielongtermlandusenoco2-noclimatechange-sresa1gdppercapita" , "http://metadata.demo.52north.org/glues-lod/record/glues:pik:metadata:dataset:magpielongtermlanduseco2-mpi-echam5-sresb1gdppercapita" , "http://metadata.demo.52north.org/glues-lod/record/glues:pik:metadata:dataset:magpielongtermlandusenoco2-ukmo-hadcm3-sresb2gdppercapita" , "http://metadata.demo.52north.org/glues-lod/record/glues:pik:metadata:dataset:magpielongtermlanduseco2-noclimatechange-sresb1gdppercapita" , "http://metadata.demo.52north.org/glues-lod/record/glues:pik:metadata:dataset:magpielongtermlandusenoco2-noclimatechange-sresb1gdppercapita" , "http://metadata.demo.52north.org/glues-lod/record/glues:pik:metadata:dataset:magpielongtermlandusenoco2-mpi-echam5-sresa1gdppercapita" , "http://metadata.demo.52north.org/glues-lod/record/glues:pik:metadata:dataset:magpielongtermlandusenoco2-ukmo-hadcm3-sresa1gdppercapita" , "http://metadata.demo.52north.org/glues-lod/record/glues:pik:metadata:dataset:magpielongtermlandusenoco2-mpi-echam5-sresb1gdppercapita" , "http://metadata.demo.52north.org/glues-lod/record/glues:pik:metadata:dataset:magpielongtermlandusenoco2-ukmo-hadcm3-sresb1gdppercapita" , "http://metadata.demo.52north.org/glues-lod/record/glues:pik:metadata:dataset:magpielongtermlanduseco2-echo-g-sresa2gdppercapita" , "http://metadata.demo.52north.org/glues-lod/record/glues:pik:metadata:dataset:magpielongtermlandusenoco2-echo-g-sresa2gdppercapita" , "http://metadata.demo.52north.org/glues-lod/record/glues:kei:metadata:dataset:grossdomesticproduct-grossdomesticproduct" , "http://metadata.demo.52north.org/glues-lod/record/glues:pik:metadata:dataset:magpielongtermlandusenoco2-mpi-echam5-sresb2gdppercapita" , "http://metadata.demo.52north.org/glues-lod/record/glues:pik:metadata:dataset:magpielongtermlanduseco2-echo-g-sresb2gdppercapita" , "http://metadata.demo.52north.org/glues-lod/record/glues:pik:metadata:dataset:magpielongtermlandusenoco2-echo-g-sresb2gdppercapita" , "http://metadata.demo.52north.org/glues-lod/record/glues:pik:metadata:dataset:magpielongtermlanduseco2-ukmo-hadcm3-sresa2gdppercapita" , "http://metadata.demo.52north.org/glues-lod/record/glues:pik:metadata:dataset:magpielongtermlanduseco2-echo-g-sresa1gdppercapita" , "http://metadata.demo.52north.org/glues-lod/record/glues:pik:metadata:dataset:magpielongtermlandusenoco2-echo-g-sresa1gdppercapita" , "http://metadata.demo.52north.org/glues-lod/record/glues:pik:metadata:dataset:magpielongtermlanduseco2-mpi-echam5-sresa2gdppercapita" , "http://metadata.demo.52north.org/glues-lod/record/glues:pik:metadata:dataset:magpielongtermlanduseco2-ukmo-hadcm3-sresb2gdppercapita" , "http://metadata.demo.52north.org/glues-lod/record/glues:pik:metadata:dataset:magpielongtermlanduseco2-noclimatechange-sresa2gdppercapita" , "http://metadata.demo.52north.org/glues-lod/record/glues:pik:metadata:dataset:magpielongtermlandusenoco2-noclimatechange-sresa2gdppercapita" , "http://metadata.demo.52north.org/glues-lod/record/glues:pik:metadata:dataset:magpielongtermlanduseco2-echo-g-sresb1gdppercapita" , "http://metadata.demo.52north.org/glues-lod/record/glues:pik:metadata:dataset:magpielongtermlandusenoco2-echo-g-sresb1gdppercapita" ]}
]
}
